Metadata-Version: 1.0
Name: legend-assistant
Version: 1.0.0
Summary: Automate legendary quest completion
Home-page: UNKNOWN
Author: 大豆
Author-email: UNKNOWN
License: MIT
Platform: UNKNOWN
